surfboard/__init__.py
surfboard/__main__.py
surfboard/app.py
surfboard/cli.py
surfboard/cli_interactive.py
surfboard/exchanges.py
surfboard/filesystem.py
surfboard/inspect.py
surfboard/project.py
surfboard-test/__init__.py
surfboard-test/__main__.py
surfboard_gregrebin-0.0.2.dist-info/LICENSE.md
surfboard_gregrebin-0.0.2.dist-info/METADATA
surfboard_gregrebin-0.0.2.dist-info/WHEEL
surfboard_gregrebin-0.0.2.dist-info/top_level.txt
surfboard_gregrebin-0.0.2.dist-info/RECORD
