Metadata-Version: 2.1
Name: surfboard-gregrebin
Version: 0.0.2
Summary: surfboard
Home-page: https://github.com/gregrebin/surfboard
Author: Greg Rebin
Author-email: me@gregrebin.com
License: UNKNOWN
Project-URL: Bug Trackers, https://github.com/gregrebin/surfboard/issues
Platform: UNKNOWN
Classifier: Programming Language :: Python :: 3
Classifier: License :: OSI Approved :: MIT License
Classifier: Operating System :: OS Independent
Requires-Python: >=3.6
Requires-Dist: freelancersdk
